novikovtv_parser_vk/__init__.py
novikovtv_parser_vk/parser/__init__.py
novikovtv_parser_vk/parser/main.py
novikovtv_parser_vk/parser/selenium_vk_parser/SeleniumVkParser.py
novikovtv_parser_vk/parser/selenium_vk_parser/__init__.py
novikovtv_parser_vk/util/__init__.py
novikovtv_parser_vk/util/env.py
novikovtv_parser_vk/util/singleton.py
novikovtv_parser_vk-1.0.4.dist-info/METADATA
novikovtv_parser_vk-1.0.4.dist-info/WHEEL
novikovtv_parser_vk-1.0.4.dist-info/licenses/LICENSE
novikovtv_parser_vk-1.0.4.dist-info/RECORD
