Metadata-Version: 2.4
Name: novikovtv-parser-vk
Version: 1.0.4
Summary: This is the VK search engine parser
Project-URL: Homepage, https://github.com/asianetsievskaya/parser-yandex
Author-email: Tsuedewn <kutner.co@gmail.com>, domster704 <domster704@mail.ru>
License-Expression: MIT
License-File: LICENSE
Classifier: License :: OSI Approved :: MIT License
Classifier: Operating System :: OS Independent
Classifier: Programming Language :: Python :: 3.11
Requires-Python: >=3.11
